{
  "users": [
    {
      "firstName": "Михаил",
      "email": "mihai807@mail.ru",
      "password": "M00000000",
      "id": 1
    },
    {
      "firstName": "Ruslan",
      "email": "rnagumanov57@gmail.com",
      "password": "12345678D",
      "id": 2,
      "lastName": "Nagumanov",
      "url": "https://i1.wallbox.ru/wallpapers/main/201547/9dbdf1269bf5a53.jpg"
    },
    {
      "firstName": "Моисей",
      "email": "test@mail.ru",
      "password": "M00000000",
      "id": 3
    },
    {
      "email": "test@mail.ru",
      "password": "M00000000",
      "firstName": "Bruklin",
      "id": 4
    },
    {
      "firstName": "jlkjlkjlkj",
      "email": "crcrt@inbox.ru",
      "password": "2309r8230948A",
      "id": 5
    }
  ],
  "cards": [
    {
      "src": "https://image.pngaaa.com/683/2260683-middle.png",
      "title": "Lorem, ipsum dolor.",
      "subtitle": "Lorem ipsum dolor sit.",
      "footer": "Lorem, isdfs"
    },
    {
      "src": "https://image.pngaaa.com/683/2260683-middle.png",
      "title": "Lorem, ipsum dolor.",
      "subtitle": "Lorem ipsum dolor sit.",
      "footer": "Lorem, isdfs"
    },
    {
      "src": "https://image.pngaaa.com/683/2260683-middle.png",
      "title": "Lorem, ipsum dolor.",
      "subtitle": "Lorem ipsum dolor sit.",
      "footer": "Lorem, isdfs"
    },
    {
      "src": "https://image.pngaaa.com/683/2260683-middle.png",
      "title": "Lorem, ipsum dolor.",
      "subtitle": "Lorem ipsum dolor sit.",
      "footer": "Lorem, isdfs"
    },
    {
      "src": "https://image.pngaaa.com/683/2260683-middle.png",
      "title": "Lorem, ipsum dolor.",
      "subtitle": "Lorem ipsum dolor sit.",
      "footer": "Lorem, isdfs"
    },
    {
      "src": "https://image.pngaaa.com/683/2260683-middle.png",
      "title": "Lorem, ipsum dolor.",
      "subtitle": "Lorem ipsum dolor sit.",
      "footer": "Lorem, isdfs"
    }
  ]
}